{
  "title": "Inside the Dregs",
  "description": "Gomi Jirou, a 29 year old virgin, has spent the past 9 years nerding out with his work colleagues about anime during lunch and drawing erotic doujinshi at night so he can masturbate.\n\nHowever, one day, this comfort zone of his is thrown into disarray by the introduction of a new colleague, Yumezora Kuroko, a bespectacled beauty with long, dark hair and a massive chest.\n\nIt only takes a moment to fall in love, just like how it takes a moment to lose your footing.\n\nThis is the story of a weak man's sins and sexual fixations.",
  "artist": "Amu",
  "author": "Amu",
  "cover": "https://cdn.imgchest.com/files/46acqzoll67.jpg",
  "chapters": {
    "1": {
      "title": "Inside and Outside",
      "volume": "1",
      "last_updated": "1747681761",
      "groups": {
        "Galactic Rolling Dynamite Pancake": "/proxy/api/imgchest/chapter/9rydmbvknyk"
      }
    },
    "2": {
      "title": "Regret and Lust",
      "volume": "1",
      "last_updated": "1750499915",
      "groups": {
        "Galactic Rolling Dynamite Pancake": "/proxy/api/imgchest/chapter/bp455pevn45"
      }
    },
    "3": {
      "title": "Fear and Curiosity",
      "volume": "1",
      "last_updated": "1750500810",
      "groups": {
        "Galactic Rolling Dynamite Pancake": "/proxy/api/imgchest/chapter/qe4g5jk6q7j"
      }
    },
    "4": {
      "title": "Killing Intent and Friendly Intent",
      "volume": "1",
      "last_updated": "1750500966",
      "groups": {
        "Galactic Rolling Dynamite Pancake": "/proxy/api/imgchest/chapter/bp455pebn45"
      }
    },
    "5": {
      "title": "Idiocy and Triumph",
      "volume": "1",
      "last_updated": "1750500998",
      "groups": {
        "Galactic Rolling Dynamite Pancake": "/proxy/api/imgchest/chapter/a8465wzbzyx"
      }
    },
    "6": {
      "title": "On and Off",
      "volume": "",
      "last_updated": "1750501070",
      "groups": {
        "Galactic Rolling Dynamite Pancake": "/proxy/api/imgchest/chapter/9249pw5bb7n"
      }
    },
    "7": {
      "title": "Casual and Serious",
      "volume": "",
      "last_updated": "1750501148",
      "groups": {
        "Galactic Rolling Dynamite Pancake": "/proxy/api/imgchest/chapter/na7kvmql348"
      }
    },
    "8": {
      "title": "Rejection and Acceptance",
      "volume": "",
      "last_updated": "1750501210",
      "groups": {
        "Galactic Rolling Dynamite Pancake": "/proxy/api/imgchest/chapter/5xy28am6zyl"
      }
    },
    "9": {
      "title": "Consent and Non-consent",
      "volume": "",
      "last_updated": "1750501283",
      "groups": {
        "Galactic Rolling Dynamite Pancake": "/proxy/api/imgchest/chapter/vj4jgkjb348"
      }
    },
    "10": {
      "title": "Secrets",
      "volume": "",
      "last_updated": "1750501338",
      "groups": {
        "Galactic Rolling Dynamite Pancake": "/proxy/api/imgchest/chapter/9ryd6moba7k"
      }
    },
    "11": {
      "title": "Brightness",
      "volume": "",
      "last_updated": "1750501398",
      "groups": {
        "Galactic Rolling Dynamite Pancake": "/proxy/api/imgchest/chapter/pg735g3vg4r"
      }
    },
    "12": {
      "title": "After the Dream",
      "volume": "",
      "last_updated": "1750501455",
      "groups": {
        "Galactic Rolling Dynamite Pancake": "/proxy/api/imgchest/chapter/n87wxd2oxyx"
      }
    },
    "13": {
      "title": "Answering Your Own Questions",
      "volume": "",
      "last_updated": "1750501515",
      "groups": {
        "Galactic Rolling Dynamite Pancake": "/proxy/api/imgchest/chapter/xny85v8j2yb"
      }
    },
    "14": {
      "title": "Amateur Virgin",
      "volume": "",
      "last_updated": "1750501574",
      "groups": {
        "Galactic Rolling Dynamite Pancake": "/proxy/api/imgchest/chapter/o24a8qobd7l"
      }
    }
  }
}